hipo/README.md
hipo/__init__.py
hipo/__main__.py
hipo/_pyhipo.cp39-win_amd64.pyd
hipo/_pyhipo.cp39-win_amd64.pyd.lib
hipo/bin/mpirun.exe
hipo/bin/msmpilaunchsvc.exe
hipo/bin/smpd.exe
hipo/bin/solver.exe
hipo/examples/pcg-aggregation.json
hipo/examples/solver.cpp
hipo/examples/solver.json
hipo/examples/solver.py
hipo/examples/thermal1.mtx
hipo/examples/thermal1_b.mtx
hipo/include/hipo/comm/Stream.h
hipo/include/hipo/comm/communication_tools.h
hipo/include/hipo/comm/ghost_tools.h
hipo/include/hipo/comm/graph_tools.h
hipo/include/hipo/comm/map_reduce.h
hipo/include/hipo/comm/owner_tools.h
hipo/include/hipo/comm/serial_mpi.hpp
hipo/include/hipo/comm/smpi.hpp
hipo/include/hipo/eigen_solver/EigenSolverLOBPCG.hpp
hipo/include/hipo/level_transfer/aggregation/ParLevelTransferOps_SA.hpp
hipo/include/hipo/level_transfer/classical/ParLevelTransferOps_RS.hpp
hipo/include/hipo/level_transfer/hypre_wrapper/hypre_wrapper.hpp
hipo/include/hipo/mat/COOMatrix.hpp
hipo/include/hipo/mat/CSRMatrix.hpp
hipo/include/hipo/mat/Matrix.hpp
hipo/include/hipo/mat/Matrix_fwd.hpp
hipo/include/hipo/mat/ParCSRMatrix.hpp
hipo/include/hipo/mat/ParMatrix.hpp
hipo/include/hipo/mat/Partitioner.hpp
hipo/include/hipo/mat/SpMVCommPattern.hpp
hipo/include/hipo/operators/ParOperator.hpp
hipo/include/hipo/operators/ParOperatorBase.hpp
hipo/include/hipo/operators/ParOperatorIdentity.hpp
hipo/include/hipo/operators/ParOperator_fwd.hpp
hipo/include/hipo/ops/BlasOps.hpp
hipo/include/hipo/ops/Container.hpp
hipo/include/hipo/ops/CrossOpTypes.hpp
hipo/include/hipo/ops/MatOps.hpp
hipo/include/hipo/ops/MixedBlasOps.hpp
hipo/include/hipo/ops/SpBlasOps.hpp
hipo/include/hipo/ops/SpLevelTransferOps.hpp
hipo/include/hipo/precond/ParPreconditionerAMG.hpp
hipo/include/hipo/precond/ParSmootherJacobi.hpp
hipo/include/hipo/precond/ParSmootherSOR.hpp
hipo/include/hipo/precond/ParSolverList.hpp
hipo/include/hipo/solver/ParSolverCG.hpp
hipo/include/hipo/solver/ParSolverCG_MP.hpp
hipo/include/hipo/solver/ParSolverGMRES.hpp
hipo-1.0.5.20251017.dist-info/METADATA
hipo-1.0.5.20251017.dist-info/WHEEL
hipo-1.0.5.20251017.dist-info/top_level.txt
hipo-1.0.5.20251017.dist-info/RECORD
